{"stats":{"minecraft:killed":{"minecraft:bee":5},"minecraft:mined":{"minecraft:pink_bed":2,"minecraft:grass":2,"minecraft:campfire":5,"minecraft:oxeye_daisy":1},"minecraft:picked_up":{"minecraft:charcoal":10,"minecraft:bee_nest":6,"minecraft:honey_bottle":1,"minecraft:wheat_seeds":5,"minecraft:honeycomb":26,"minecraft:oxeye_daisy":1,"minecraft:egg":1},"minecraft:used":{"minecraft:peony":9,"minecraft:glass":749,"minecraft:cornflower":3,"minecraft:acacia_door":4,"minecraft:grass_block":267,"minecraft:iron_block":528,"minecraft:oak_stairs":6,"minecraft:blue_orchid":2,"minecraft:poppy":7,"minecraft:chest":13,"minecraft:diamond_axe":5,"minecraft:bee_spawn_egg":25,"minecraft:pink_bed":3,"minecraft:torch":4,"minecraft:diamond_sword":11,"minecraft:lily_of_the_valley":5,"minecraft:crafting_table":1,"minecraft:furnace":1,"minecraft:oak_sapling":10,"minecraft:allium":10,"minecraft:campfire":22,"minecraft:bee_nest":14,"minecraft:dandelion":4,"minecraft:azure_bluet":17,"minecraft:bone_meal":100,"minecraft:honey_bottle":36,"minecraft:dark_oak_sapling":2},"minecraft:custom":{"minecraft:time_since_rest":2050,"minecraft:damage_taken":120,"minecraft:walk_one_cm":272176,"minecraft:mob_kills":5,"minecraft:damage_dealt":596,"minecraft:fly_one_cm":38828,"minecraft:open_chest":48,"minecraft:play_one_minute":149112,"minecraft:sneak_time":98,"minecraft:walk_under_water_one_cm":796,"minecraft:jump":158,"minecraft:leave_game":3,"minecraft:time_since_death":149112,"minecraft:walk_on_water_one_cm":2429,"minecraft:sleep_in_bed":9}},"DataVersion":2227}