{
    "display": {
        "icon": {
            "item": "minecraft:firework_rocket"
        },
        "title":
		{
            "text": "Ringmaster",
            "color": "white",
			"bold": true
			
		},
		"description":
		{   "text": "ELYTRA BRANCH: Finish a course, gliding through every ring in one go, without using or dropping any fireworks",
		    "italic": true,
			"color": "red",
			"bold": false
		},

		"frame": "task",
		"show_toast": true,
		"announce_to_chat": false,
		"hidden": false
    },
    "parent": "d3:folder_b/aerodynamic",
    "criteria": {
        "aerodynamic": {
            "trigger": "minecraft:impossible"
        }
    }
}