{"stats":{"minecraft:custom":{"minecraft:open_chest":10,"minecraft:time_since_rest":7683,"minecraft:play_one_minute":10358,"minecraft:sprint_one_cm":11277,"minecraft:damage_taken":20,"minecraft:walk_one_cm":34819,"minecraft:interact_with_campfire":4,"minecraft:sneak_time":92,"minecraft:walk_under_water_one_cm":3237,"minecraft:jump":54,"minecraft:damage_dealt":20,"minecraft:leave_game":3,"minecraft:time_since_death":10358,"minecraft:walk_on_water_one_cm":1356,"minecraft:sleep_in_bed":1,"minecraft:climb_one_cm":1018,"minecraft:swim_one_cm":5712,"minecraft:fall_one_cm":671,"minecraft:fly_one_cm":9546},"minecraft:mined":{"minecraft:potatoes":2,"minecraft:beetroots":1,"minecraft:carrots":1,"minecraft:sand":3,"minecraft:crafting_table":2},"minecraft:picked_up":{"minecraft:item_frame":2,"minecraft:crafting_table":2,"minecraft:cooked_mutton":1,"minecraft:cooked_porkchop":2,"minecraft:beetroot":1,"minecraft:beetroot_seeds":3,"minecraft:potato":11,"minecraft:sand":3,"minecraft:carrot":5,"minecraft:melon_slice":1},"minecraft:used":{"minecraft:item_frame":2,"minecraft:sand":3,"minecraft:crafting_table":2,"minecraft:carrot":2,"minecraft:beetroot_seeds":1,"minecraft:diamond_hoe":3,"minecraft:potato":8}},"DataVersion":1976}